fcutil/__init__.py
fcutil/fuProfiler.py
fcutil/searchList.py
fcutil-0.0.2.dist-info/METADATA
fcutil-0.0.2.dist-info/WHEEL
fcutil-0.0.2.dist-info/top_level.txt
fcutil-0.0.2.dist-info/RECORD
