Metadata-Version: 2.1
Name: fcutil
Version: 0.0.2
Summary: Piccola libreria di utility
Author: Christian Fugini
Author-email: fuginic@gmail.com
